{
  "section_index": 293,
  "section_id": "4.2.3",
  "title": "4.2.3 Status Field Definition",
  "level": 3,
  "pages": {
    "start": 165,
    "end": 167,
    "count": 3
  },
  "content": {
    "text": "The Status field defines the status for the command indicated in the completion queue entry, defined in\nFigure 100.\nA value of 0h for the Status field indicates a successful command completion, with no fatal or non-fatal error\nconditions. Unless otherwise noted, if a command fails to complete successfully for multiple reasons, then\nthe particular status code returned is chosen by the vendor.\nThe Status Code (SC) field in the completion queue entry indicates more detailed status information about\nthe completion being reported.\nEach Status Code set of values is split into three ranges:\n•\n00h to 7Fh: Applicable to Admin Command Set, Fabrics commands, or across multiple command\nsets;\nNVM Express® Base Specification, Revision 2.3\n•\n80h to BFh: I/O Command Set specific status codes, or Fabrics command specific status codes;\nand\n•\nC0h to FFh: Vendor Specific status codes.\nUnless otherwise specified, if multiple status codes apply, then the controller selects the status code that is\nreturned.",
    "tables": [],
    "figures": [
      {
        "id": "figure_165_666",
        "page": 165,
        "bbox": [
          114.0,
          666.0,
          881.0,
          804.0
        ],
        "detected_title": "Figure 100: Completion Queue Entry: Status Field",
        "title": "Figure 100: Completion Queue Entry: Status Field",
        "image_path": "Figure_4_2_3_Status_Field_Definition.png",
        "merged_count": 3
      }
    ]
  },
  "statistics": {
    "table_count": 0,
    "figure_count": 1
  }
}