{
  "section_index": 730,
  "section_id": "8.1.16.2",
  "title": "8.1.16.2 Namespace Deletion Asynchronous Event Reporting",
  "level": 4,
  "pages": {
    "start": 607,
    "end": 608,
    "count": 2
  },
  "content": {
    "text": "If a delete operation is requested for a namespace:\n•\nvia a command (e.g., a Namespace Management command or Capacity Management command)\nreceived on the Admin Submission Queue (e.g., not via a Management Endpoint, refer to the NVM\nExpress Management Interface Specification), then:\neach controller, to which the namespace is attached, that has Attached Namespace\nAttribute Notices enabled (refer to Figure 409) other than the controller processing that\ndelete operation, shall issue an Attached Namespace Attribute Changed asynchronous\nevent as part of the delete operation to indicate a namespace change; and\neach controller that has Allocated Namespace Attribute Notices enabled (refer to Figure\n409) other than the controller processing that delete operation, shall issue an Allocated\nNamespace Attribute Changed asynchronous event as part of the delete operation to\nindicate a namespace change;\nor\n•\nvia any other method (e.g., a method outside the scope of this specification or via a Management\nEndpoint, refer to the NVM Express Management Interface Specification), then:\neach controller, to which the namespace is attached, that has Attached Namespace\nAttribute Notices enabled (refer to Figure 409) shall issue an Attached Namespace\nAttribute Changed asynchronous event as part of the delete operation to indicate a\nnamespace change; and\neach controller that has Allocated Namespace Attribute Notices enabled (refer to Figure\n409) shall issue an Allocated Namespace Attribute Changed asynchronous event as part\nof the delete operation to indicate a namespace change.",
    "tables": [],
    "figures": []
  },
  "statistics": {
    "table_count": 0,
    "figure_count": 0
  }
}