{
  "section_index": 95,
  "section_id": "4.2.3.3",
  "title": "4.2.3.3 SP (M)",
  "level": 4,
  "pages": {
    "start": 50,
    "end": 50,
    "count": 1
  },
  "content": {
    "text": "The SP table is defined in [2], and Table 29 defines the Preconfiguration Data for the SP table.\n*SP1 means that this row only exists in the Admin SP's OFS when the Locking SP is created by the manufacturer.\n\n[Table: table_50_774]\n",
    "tables": [
      {
        "table_id": "table_50_774",
        "title": null,
        "page": 50,
        "bbox": [
          100.98,
          613.008,
          508.572,
          748.44
        ],
        "image_path": "table_50_774.png",
        "markdown": "| UID | Name | ORG | EffectiveAuth | DateOfIssue | Bytes | LifeCycle | Frozen |\n|:---|:---|:---|:---|:---|:---|:---|:---|\n| 00 00 02 05 00 00 00 01 | \"Admin\" | | | | | Manufactured | FALSE |\n| 00 00 02 05 00 00 00 02 | \"Locking\" | | | | | Manufactured-Inactive | FALSE |\n| *SP1 | | | | | | | |",
        "table_md": "| UID | Name | ORG | EffectiveAuth | DateOfIssue | Bytes | LifeCycle | Frozen |\n|:---|:---|:---|:---|:---|:---|:---|:---|\n| 00 00 02 05 00 00 00 01 | \"Admin\" | | | | | Manufactured | FALSE |\n| 00 00 02 05 00 00 00 02 | \"Locking\" | | | | | Manufactured-Inactive | FALSE |\n| *SP1 | | | | | | | |"
      }
    ],
    "figures": []
  },
  "statistics": {
    "table_count": 1,
    "figure_count": 0
  }
}