{
  "section_index": 105,
  "section_id": "4.2.6.1",
  "title": "4.2.6.1 DataRemovalMechanism (ObjectTable)",
  "level": 4,
  "pages": {
    "start": 51,
    "end": 51,
    "count": 1
  },
  "content": {
    "text": "4.2.6.1 DataRemovalMechanism (ObjectTable) \nThe DataRemovalMchanism table is defined in Table 32 \nTable 32 - DataRemovalMechansim Table Description ",
    "tables": [
      {
        "table_id": "Table_51_2",
        "title": "Table 32 - DataRemovalMechansim Table Description",
        "page": 51,
        "bbox": [
          43.74000120162964,
          570.8520263671875,
          568.260009765625,
          608.6880126953125
        ],
        "image_path": "table_051_2.png",
        "markdown": null,
        "table_md": "| Column Number | Column Name | IsUnique | Column Type |\n|---|---|---|---|\n| 0x00 | UID | | uid |\n| 0x01 | ActiveDataRemovalMechanism | | data_removal_mechanism |"
      }
    ],
    "figures": []
  },
  "statistics": {
    "table_count": 1,
    "figure_count": 0
  }
}