{
  "section_index": 4,
  "section_id": "1.3.1",
  "title": "1.3.1 Compliance",
  "level": 3,
  "pages": {
    "start": 5,
    "end": 5,
    "count": 1
  },
  "content": {
    "text": "All products seeking OCP Inspired™ or OCP Accepted ™ Product Recognition shall comply with the\nOCP Hardware Management Baseline Profile V1.0  and provide such evidence by completing the\nHardware Management Tab in the 2021 Supplier Requirements Checklist.",
    "tables": [],
    "figures": []
  },
  "statistics": {
    "table_count": 0,
    "figure_count": 0
  }
}